[
    {
        "id": "word001",
        "word": "ありがとう",
        "pronunciation": "arigatou",
        "meaning": "thank you",
        "part_of_speech": "expression",
        "difficulty": "easy",
        "lesson_no": 1,
        "when_to_say": "Used to express gratitude in informal settings.",
        "example": "ありがとう、手伝ってくれて！ (arigatou, tetsudatte kurete!) - Thank you for helping me!"
    },
    {
        "id": "word002",
        "word": "さようなら",
        "pronunciation": "sayounara",
        "meaning": "goodbye",
        "part_of_speech": "expression",
        "difficulty": "easy",
        "lesson_no": 1,
        "when_to_say": "Used when parting from someone, typically for a long time.",
        "example": "友達にさようならを言いました。(Tomodachi ni sayounara o iimashita.) - I said goodbye to my friend."
    },
    {
        "id": "word035",
        "word": "車",
        "pronunciation": "kuruma",
        "meaning": "car",
        "part_of_speech": "noun",
        "difficulty": "easy",
        "lesson_no": 2,
        "when_to_say": "Used when talking about vehicles or transportation.",
        "example": "車で行きます。(Kuruma de ikimasu.) - I will go by car."
    },
    {
        "id": "word036",
        "word": "新しい",
        "pronunciation": "atarashii",
        "meaning": "new",
        "part_of_speech": "adjective",
        "difficulty": "medium",
        "lesson_no": 5,
        "when_to_say": "Used when describing something that is new or recently made.",
        "example": "新しい家です。(Atarashii ie desu.) - It is a new house."
    },
    {
        "id": "word037",
        "word": "古い",
        "pronunciation": "furui",
        "meaning": "old",
        "part_of_speech": "adjective",
        "difficulty": "medium",
        "lesson_no": 5,
        "when_to_say": "Used when describing something that is old or aged.",
        "example": "古い本があります。(Furui hon ga arimasu.) - I have an old book."
    },
    {
        "id": "word038",
        "word": "早い",
        "pronunciation": "hayai",
        "meaning": "fast, early",
        "part_of_speech": "adjective",
        "difficulty": "medium",
        "lesson_no": 4,
        "when_to_say": "Used when describing speed or time.",
        "example": "彼はとても早いです。(Kare wa totemo hayai desu.) - He is very fast."
    },
    {
        "id": "word039",
        "word": "遅い",
        "pronunciation": "osoi",
        "meaning": "slow, late",
        "part_of_speech": "adjective",
        "difficulty": "medium",
        "lesson_no": 4,
        "when_to_say": "Used when describing slowness or tardiness.",
        "example": "バスは遅れています。(Basu wa okureteimasu.) - The bus is late."
    },
    {
        "id": "word040",
        "word": "食べる",
        "pronunciation": "taberu",
        "meaning": "to eat",
        "part_of_speech": "verb",
        "difficulty": "easy",
        "lesson_no": 2,
        "when_to_say": "Used when referring to consuming food.",
        "example": "寿司を食べます。(Sushi o tabemasu.) - I eat sushi."
    },
    {
        "id": "word041",
        "word": "飲む",
        "pronunciation": "nomu",
        "meaning": "to drink",
        "part_of_speech": "verb",
        "difficulty": "easy",
        "lesson_no": 2,
        "when_to_say": "Used when referring to consuming beverages.",
        "example": "お茶を飲みます。(Ocha o nomimasu.) - I drink tea."
    },
    {
        "id": "word042",
        "word": "見る",
        "pronunciation": "miru",
        "meaning": "to see, to watch",
        "part_of_speech": "verb",
        "difficulty": "easy",
        "lesson_no": 3,
        "when_to_say": "Used when referring to seeing or observing something.",
        "example": "映画を見ます。(Eiga o mimasu.) - I watch a movie."
    },
    {
        "id": "word043",
        "word": "聞く",
        "pronunciation": "kiku",
        "meaning": "to listen, to ask",
        "part_of_speech": "verb",
        "difficulty": "easy",
        "lesson_no": 3,
        "when_to_say": "Used when referring to listening or inquiring.",
        "example": "音楽を聞きます。(Ongaku o kikimasu.) - I listen to music."
    },
    {
        "id": "word044",
        "word": "会う",
        "pronunciation": "au",
        "meaning": "to meet",
        "part_of_speech": "verb",
        "difficulty": "easy",
        "lesson_no": 3,
        "when_to_say": "Used when referring to meeting someone.",
        "example": "友達に会います。(Tomodachi ni aimasu.) - I will meet my friend."
    },
    {
        "id": "word045",
        "word": "走る",
        "pronunciation": "hashiru",
        "meaning": "to run",
        "part_of_speech": "verb",
        "difficulty": "easy",
        "lesson_no": 4,
        "when_to_say": "Used when referring to running.",
        "example": "公園で走ります。(Kouen de hashirimasu.) - I run in the park."
    },
    {
        "id": "word046",
        "word": "買う",
        "pronunciation": "kau",
        "meaning": "to buy",
        "part_of_speech": "verb",
        "difficulty": "easy",
        "lesson_no": 2,
        "when_to_say": "Used when referring to purchasing something.",
        "example": "りんごを買います。(Ringo o kaimasu.) - I buy apples."
    },
    {
        "id": "word047",
        "word": "売る",
        "pronunciation": "uru",
        "meaning": "to sell",
        "part_of_speech": "verb",
        "difficulty": "medium",
        "lesson_no": 6,
        "when_to_say": "Used when referring to selling goods.",
        "example": "店で本を売ります。(Mise de hon o urimasu.) - I sell books at the store."
    },
    {
        "id": "word048",
        "word": "高い",
        "pronunciation": "takai",
        "meaning": "expensive, tall",
        "part_of_speech": "adjective",
        "difficulty": "medium",
        "lesson_no": 5,
        "when_to_say": "Used when describing height or cost.",
        "example": "この家は高いです。(Kono ie wa takai desu.) - This house is expensive."
    },
    {
        "id": "word049",
        "word": "安い",
        "pronunciation": "yasui",
        "meaning": "cheap, inexpensive",
        "part_of_speech": "adjective",
        "difficulty": "medium",
        "lesson_no": 5,
        "when_to_say": "Used when describing affordability.",
        "example": "このペンは安いです。(Kono pen wa yasui desu.) - This pen is cheap."
    },
    {
        "id": "word050",
        "word": "晴れ",
        "pronunciation": "hare",
        "meaning": "sunny",
        "part_of_speech": "noun",
        "difficulty": "easy",
        "lesson_no": 4,
        "when_to_say": "Used when describing clear weather.",
        "example": "今日は晴れです。(Kyou wa hare desu.) - It is sunny today."
    },
    {
        "id": "word051",
        "word": "雨",
        "pronunciation": "ame",
        "meaning": "rain",
        "part_of_speech": "noun",
        "difficulty": "easy",
        "lesson_no": 4,
        "when_to_say": "Used when describing rainy weather.",
        "example": "雨が降っています。(Ame ga futteimasu.) - It is raining."
    },
    {
        "id": "word052",
        "word": "雪",
        "pronunciation": "yuki",
        "meaning": "snow",
        "part_of_speech": "noun",
        "difficulty": "easy",
        "lesson_no": 4,
        "when_to_say": "Used when describing snowy weather.",
        "example": "山に雪があります。(Yama ni yuki ga arimasu.) - There is snow on the mountain."
    },
    {
        "id": "word053",
        "word": "風",
        "pronunciation": "kaze",
        "meaning": "wind",
        "part_of_speech": "noun",
        "difficulty": "easy",
        "lesson_no": 4,
        "when_to_say": "Used when describing windy conditions.",
        "example": "風が強いです。(Kaze ga tsuyoi desu.) - The wind is strong."
    },
    {
        "id": "word054",
        "word": "太陽",
        "pronunciation": "taiyou",
        "meaning": "sun",
        "part_of_speech": "noun",
        "difficulty": "easy",
        "lesson_no": 3,
        "when_to_say": "Used when referring to the sun.",
        "example": "太陽が昇ります。(Taiyou ga noborimasu.) - The sun rises."
    },
    {
        "id": "word055",
        "word": "月",
        "pronunciation": "tsuki",
        "meaning": "moon",
        "part_of_speech": "noun",
        "difficulty": "easy",
        "lesson_no": 3,
        "when_to_say": "Used when referring to the moon.",
        "example": "月がきれいです。(Tsuki ga kirei desu.) - The moon is beautiful."
    },
    {
        "id": "word056",
        "word": "星",
        "pronunciation": "hoshi",
        "meaning": "star",
        "part_of_speech": "noun",
        "difficulty": "easy",
        "lesson_no": 3,
        "when_to_say": "Used when referring to stars.",
        "example": "星がたくさん見えます。(Hoshi ga takusan miemasu.) - Many stars are visible."
    },
    {
        "id": "word057",
        "word": "空",
        "pronunciation": "sora",
        "meaning": "sky",
        "part_of_speech": "noun",
        "difficulty": "easy",
        "lesson_no": 3,
        "when_to_say": "Used when referring to the sky.",
        "example": "空が青いです。(Sora ga aoi desu.) - The sky is blue."
    },
    {
        "id": "word058",
        "word": "川",
        "pronunciation": "kawa",
        "meaning": "river",
        "part_of_speech": "noun",
        "difficulty": "easy",
        "lesson_no": 4,
        "when_to_say": "Used when referring to rivers or streams.",
        "example": "川で泳ぎます。(Kawa de oyogimasu.) - I swim in the river."
    },
    {
        "id": "word059",
        "word": "山",
        "pronunciation": "yama",
        "meaning": "mountain",
        "part_of_speech": "noun",
        "difficulty": "easy",
        "lesson_no": 4,
        "when_to_say": "Used when referring to mountains.",
        "example": "山に登ります。(Yama ni noborimasu.) - I climb mountains."
    },
    {
        "id": "word060",
        "word": "海",
        "pronunciation": "umi",
        "meaning": "sea",
        "part_of_speech": "noun",
        "difficulty": "easy",
        "lesson_no": 4,
        "when_to_say": "Used when referring to the sea or ocean.",
        "example": "海で泳ぎます。(Umi de oyogimasu.) - I swim in the sea."
    },
    {
        "id": "word061",
        "word": "森",
        "pronunciation": "mori",
        "meaning": "forest",
        "part_of_speech": "noun",
        "difficulty": "medium",
        "lesson_no": 6,
        "when_to_say": "Used when referring to forests or woods.",
        "example": "森で散歩します。(Mori de sanpo shimasu.) - I walk in the forest."
    },
    {
        "id": "word062",
        "word": "花",
        "pronunciation": "hana",
        "meaning": "flower",
        "part_of_speech": "noun",
        "difficulty": "easy",
        "lesson_no": 3,
        "when_to_say": "Used when referring to flowers.",
        "example": "花が咲きます。(Hana ga sakimasu.) - Flowers bloom."
    },
    {
        "id": "word063",
        "word": "鳥",
        "pronunciation": "tori",
        "meaning": "bird",
        "part_of_speech": "noun",
        "difficulty": "easy",
        "lesson_no": 3,
        "when_to_say": "Used when referring to birds.",
        "example": "鳥が飛んでいます。(Tori ga tondeimasu.) - The bird is flying."
    }
]